odoo/addons/l10n_th_tax_invoice/README.rst
odoo/addons/l10n_th_tax_invoice/__init__.py
odoo/addons/l10n_th_tax_invoice/__manifest__.py
odoo/addons/l10n_th_tax_invoice/i18n/l10n_th_tax_invoice.pot
odoo/addons/l10n_th_tax_invoice/i18n/th.po
odoo/addons/l10n_th_tax_invoice/migrations/13.0.2.0.0/post-migration.py
odoo/addons/l10n_th_tax_invoice/models/__init__.py
odoo/addons/l10n_th_tax_invoice/models/account.py
odoo/addons/l10n_th_tax_invoice/models/account_move.py
odoo/addons/l10n_th_tax_invoice/models/account_payment.py
odoo/addons/l10n_th_tax_invoice/readme/CONFIGURE.rst
odoo/addons/l10n_th_tax_invoice/readme/CONTRIBUTORS.rst
odoo/addons/l10n_th_tax_invoice/readme/DESCRIPTION.rst
odoo/addons/l10n_th_tax_invoice/readme/USAGE.rst
odoo/addons/l10n_th_tax_invoice/security/ir.model.access.csv
odoo/addons/l10n_th_tax_invoice/static/description/icon.png
odoo/addons/l10n_th_tax_invoice/static/description/index.html
odoo/addons/l10n_th_tax_invoice/tests/__init__.py
odoo/addons/l10n_th_tax_invoice/tests/test_tax_invoice.py
odoo/addons/l10n_th_tax_invoice/views/account_move_view.xml
odoo/addons/l10n_th_tax_invoice/views/account_payment_view.xml
odoo/addons/l10n_th_tax_invoice/views/account_view.xml
odoo13_addon_l10n_th_tax_invoice-13.0.2.2.4.dist-info/METADATA
odoo13_addon_l10n_th_tax_invoice-13.0.2.2.4.dist-info/WHEEL
odoo13_addon_l10n_th_tax_invoice-13.0.2.2.4.dist-info/top_level.txt
odoo13_addon_l10n_th_tax_invoice-13.0.2.2.4.dist-info/RECORD
