Metadata-Version: 2.1
Name: odoo13-addon-l10n-th-tax-invoice
Version: 13.0.2.2.4
Summary: Thai Localization - Account Tax Invoice
Home-page: https://github.com/OCA/l10n-thailand/
Author: Ecosoft,Odoo Community Association (OCA)
Author-email: support@odoo-community.org
License: AGPL-3
Platform: UNKNOWN
Classifier: Programming Language :: Python
Classifier: Framework :: Odoo
Classifier: License :: OSI Approved :: GNU Affero General Public License v3
Classifier: Development Status :: 3 - Alpha
Requires-Python: >=3.5
Requires-Dist: odoo (<13.1dev,>=13.0a)
